_pysha3.cp36-win_amd64.pyd
sha3.py
pysha3-1.0.2.dist-info/DESCRIPTION.rst
pysha3-1.0.2.dist-info/METADATA
pysha3-1.0.2.dist-info/RECORD
pysha3-1.0.2.dist-info/WHEEL
pysha3-1.0.2.dist-info/metadata.json
pysha3-1.0.2.dist-info/top_level.txt
